pyetbd/__init__.py
pyetbd/algorithm.py
pyetbd/algorithm_strategies/__init__.py
pyetbd/algorithm_strategies/fdf_sampling_strategies.py
pyetbd/algorithm_strategies/fitness_calculation_strategies.py
pyetbd/algorithm_strategies/mutation_strategies.py
pyetbd/algorithm_strategies/punishment_strategies.py
pyetbd/algorithm_strategies/recombination_strategies.py
pyetbd/algorithm_strategies/selection_strategies.py
pyetbd/data_saver.py
pyetbd/defaults.py
pyetbd/experiment.py
pyetbd/experiment_gui.py
pyetbd/experiment_runner.py
pyetbd/organisms.py
pyetbd/rules/__init__.py
pyetbd/rules/fdfs.py
pyetbd/rules/fitness_calculation.py
pyetbd/rules/mutation.py
pyetbd/rules/punishment.py
pyetbd/rules/recombination.py
pyetbd/rules/selection.py
pyetbd/schedules.py
pyetbd/settings_classes.py
pyetbd/utils/__init__.py
pyetbd/utils/binary_converter.py
pyetbd/utils/equations.py
pyetbd/utils/progress_logger.py
pyetbd/utils/timer.py
pyetbd-0.2.1.dist-info/LICENSE
pyetbd-0.2.1.dist-info/METADATA
pyetbd-0.2.1.dist-info/WHEEL
pyetbd-0.2.1.dist-info/RECORD
