Metadata-Version: 2.1
Name: pyetbd
Version: 0.2.1
Summary: McDowell's (2004) ETBD implemented in Python.
License: MIT
Author: ryhigg
Author-email: ryanhigginbotham@ufl.edu
Requires-Python: >=3.10,<4.0
Classifier: License :: OSI Approved :: MIT License
Classifier: Programming Language :: Python :: 3
Classifier: Programming Language :: Python :: 3.10
Classifier: Programming Language :: Python :: 3.11
Classifier: Programming Language :: Python :: 3.12
Requires-Dist: memory-profiler (>=0.61.0,<0.62.0)
Requires-Dist: numba (==0.57.1)
Requires-Dist: numpy (==1.24.4)
Requires-Dist: openpyxl (==3.0.10)
Requires-Dist: pandas (==2.1.0)
